					<boardgame objectid="226">
			<minplayers>2</minplayers>
			<maxplayers>2</maxplayers>
			<playingtime>30</playingtime>
			<age>12</age>
							<name primary="true" sortindex="1">Isi</name>
							<thumbnail>https://cf.geekdo-images.com/thumb/img/2EvmsiLRwD23lPI2mSXjCdpNgL8=/fit-in/200x150/pic296559.jpg</thumbnail>
				<image>https://cf.geekdo-images.com/original/img/mm9qLpLm7z4UBsmiyymr4maZiQE=/0x0/pic296559.jpg</image>
															<boardgamecategory objectid="1009">Abstract Strategy</boardgamecategory>
															<boardgamemechanic objectid="2011">Modular Board</boardgamemechanic>
															<boardgamemechanic objectid="2081">Network and Route Building</boardgamemechanic>
					<average>6.57051</average>
