					<boardgame objectid="246">
			<minplayers>3</minplayers>
			<maxplayers>7</maxplayers>
			<playingtime>0</playingtime>
			<age>0</age>
							<name primary="true" sortindex="1">Politika</name>
							<thumbnail>https://cf.geekdo-images.com/thumb/img/7878KKRmhfDH5rsutd00-sC817s=/fit-in/200x150/pic1300732.jpg</thumbnail>
				<image>https://cf.geekdo-images.com/original/img/17gXkneX1EKpt23Bx2pEEjAqfZM=/0x0/pic1300732.jpg</image>
															<boardgamecategory objectid="1002">Card Game</boardgamecategory>
															<boardgamecategory objectid="1001">Political</boardgamecategory>
					<average>4.48936</average>
