					<boardgame objectid="292">
			<minplayers>3</minplayers>
			<maxplayers>5</maxplayers>
			<playingtime>30</playingtime>
			<age>8</age>
							<name primary="true" sortindex="1">Attacke</name>
							<thumbnail>https://cf.geekdo-images.com/thumb/img/wDxmZaLZciq_u5yyQoQgnmiM5Eg=/fit-in/200x150/pic231849.jpg</thumbnail>
				<image>https://cf.geekdo-images.com/original/img/9NYQturJ3MQabfDm6MEnvdn70Rg=/0x0/pic231849.jpg</image>
															<boardgamemechanic objectid="2012">Auction/Bidding</boardgamemechanic>
															<boardgamecategory objectid="1002">Card Game</boardgamecategory>
															<boardgamemechanic objectid="2040">Hand Management</boardgamemechanic>
															<boardgamecategory objectid="1035">Medieval</boardgamecategory>
																													<boardgamemechanic objectid="2004">Set Collection</boardgamemechanic>
					<average>5.70759</average>
